CHANGELOG
LICENSE
MANIFEST.in
README.rst
setup.py
rgf/__init__.py
rgf/dsl.py
rgf.egg-info/PKG-INFO
rgf.egg-info/SOURCES.txt
rgf.egg-info/dependency_links.txt
rgf.egg-info/entry_points.txt
rgf.egg-info/top_level.txt
rgf/core/__init__.py
rgf/core/runner.py
rgf/core/examples/__init__.py
rgf/core/examples/example.py
rgf/core/examples/example_group.py
rgf/core/examples/example_result.py
rgf/core/examples/example_suite.py