Metadata-Version: 1.0
Name: rgf
Version: 0.2.0
Summary: rgf: red/green/refactor, a BDD framework for writing and running specs.
Home-page: http://github.com/fidothe/rgf
Author: Matt Patterson
Author-email: matt@reprocessed.org
License: LICENSE
Keywords: testing bdd tdd
Platform: UNKNOWN
Classifier: Environment :: Console
Classifier: Development Status :: 3 - Alpha
Classifier: Intended Audience :: Developers
Classifier: License :: OSI Approved :: MIT License
Classifier: Operating System :: Unix
Classifier: Topic :: Software Development :: Testing
